README.md
setup.py
dblpct/__init__.py
dblpct/dblpct.py
dblpct.egg-info/PKG-INFO
dblpct.egg-info/SOURCES.txt
dblpct.egg-info/dependency_links.txt
dblpct.egg-info/entry_points.txt
dblpct.egg-info/top_level.txt
tests/__init__.py
tests/test_dblpct.py