Metadata-Version: 2.1
Name: dblpct
Version: 20220114.2
Summary: double the % to two.
Home-page: https://github.com/mollinaca/dblpct
Author: mollinaca
Author-email: mail@mollinaca.dev
License: CC0
Platform: UNKNOWN
